vidstream/__init__.py
vidstream/audio.py
vidstream/streaming.py
vidstreamv2-1.0.dist-info/LICENSE
vidstreamv2-1.0.dist-info/METADATA
vidstreamv2-1.0.dist-info/WHEEL
vidstreamv2-1.0.dist-info/top_level.txt
vidstreamv2-1.0.dist-info/RECORD
