Metadata-Version: 2.1
Name: vidstreamv2
Version: 1.0
Summary: Stream video data
Author: pluizzb
Author-email: pluizzb@gmail.com
Keywords: python,video,stream,video stream,camera stream,sockets
Classifier: Development Status :: 1 - Planning
Classifier: Intended Audience :: Developers
Classifier: Programming Language :: Python :: 3
Classifier: Operating System :: Unix
Classifier: Operating System :: MacOS :: MacOS X
Classifier: Operating System :: Microsoft :: Windows
License-File: LICENSE
Requires-Dist: opencv-python
Requires-Dist: pyautogui
Requires-Dist: pyaudio
